tidalotter/__init__.py
tidalotter/main.py
tidalotter-1.2.2.dist-info/METADATA
tidalotter-1.2.2.dist-info/WHEEL
tidalotter-1.2.2.dist-info/entry_points.txt
tidalotter-1.2.2.dist-info/licenses/LICENSE.md
tidalotter-1.2.2.dist-info/RECORD
