Metadata-Version: 2.4
Name: tidalotter
Version: 1.2.2
Summary: A TIDAL download CLI, using Otter LLC's API.
Project-URL: Homepage, https://github.com/ItsThatOneJack-Dev/tidalotter
Project-URL: Repository, https://github.com/ItsThatOneJack-Dev/tidalotter
Project-URL: Issues, https://github.com/ItsThatOneJack-Dev/tidalotter/issues
Author-email: ItsThatOneJack <jack@itoj.dev>
License: # 🏳️‍🌈 Opinionated Queer License v1.2 (Sharealike)
License-File: LICENSE.md
Classifier: Development Status :: 3 - Alpha
Classifier: Intended Audience :: Developers
Classifier: Intended Audience :: End Users/Desktop
Classifier: License :: Other/Proprietary License
Classifier: Programming Language :: Python :: 3
Classifier: Programming Language :: Python :: 3.8
Classifier: Programming Language :: Python :: 3.9
Classifier: Programming Language :: Python :: 3.10
Classifier: Programming Language :: Python :: 3.11
Classifier: Programming Language :: Python :: 3.12
Requires-Python: >=3.12
Requires-Dist: requests>=2.32.4
Requires-Dist: rich>=14.0.0
